<?xml version="1.0" encoding="ISO-8859-1"?>
<configuration version="4.0">
 <groups/>
 <projectEnvironments>
  <projectEnvironment name="GNU GCC Eclipse CDT (Default)" uuid="ccdc8d34-b494-48db-8e8c-ca65d0a42b43">
   <properties>
    <property flags="0x90040049" name="Compiler Defines" type="String" value="ATOMICS_USER_MULTICORE_CASE=0, ATOMICS_USE_GENERIC_IMPL=1, CANSM_NO_SYMBOLS_WITHOUT_PREFIX, COMM_DONT_PROVIDE_LEGACY_SYMBOLIC_NAMES, COMPILERCFG_EXTENSION_MCAL_FILE, DISABLE_MCAL_INTERMODULE_ASR_CHECK, ECUM_PROVIDE_LEGACY_SYMBOLIC_NAMES, HIDE_IAR_SPECIFIC, KU8_GLOBAL_NUMBER_OF_SOLENOIDS=4, NM_DONT_PROVIDE_LEGACY_SYMBOLIC_NAMES, OSIARARM, OS_ARCH=OS_CORTEXM, OS_CPU=OS_S32K14X, OS_DEVELOPMENT_SANITY_CHECKS=0, OS_INITCORE=0, OS_KERNEL_TYPE=OS_SYSTEM_CALL, OS_MEMMAP=0, OS_N_CORES=1, OS_RELEASE_SUFFIX=OS_AS403, OS_SCHEDULING_ALGORITHM=OS_CLZ_QUEUE, OS_TOOL=OS_iar, OS_USE_TRACE=0, TS_ARCH_DERIVATE=TS_S32K14X, TS_ARCH_FAMILY=TS_CORTEXM, _IAR_C_S32K14x_, __AT=, __CALIBRATION__(x)=, __ICCARM__, __RAM_SHADOW__(x)=, __ROM_DEFAULT__(x)=, __no_init="/>
   </properties>
  </projectEnvironment>
  <projectEnvironment name="GNU GCC (C++) Eclipse CDT (Default)" uuid="c9460017-70ff-4e06-a667-02f185ce5da6">
   <properties/>
  </projectEnvironment>
 </projectEnvironments>
</configuration>
